florg-1.0.0.dist-info/licenses/LICENSE
organize/__init__.py
organize/cli.py
organize/filters.py
organize/grouper.py
organize/history.py
organize/preview.py
organize/renamer.py
organize/utils.py
florg-1.0.0.dist-info/METADATA
florg-1.0.0.dist-info/WHEEL
florg-1.0.0.dist-info/entry_points.txt
florg-1.0.0.dist-info/top_level.txt
florg-1.0.0.dist-info/RECORD
