Metadata-Version: 2.4
Name: florg
Version: 1.0.0
Summary: A CLI tool for batch file renaming and organizing
Home-page: https://github.com/laisario/florg
Author: Laísa Rio
License: MIT
Project-URL: Homepage, https://github.com/laisario/florg
Project-URL: Documentation, https://github.com/laisario/florg#readme
Project-URL: Repository, https://github.com/laisario/florg
Project-URL: Bug Tracker, https://github.com/laisario/florg/issues
Keywords: file,organizer,renamer,batch,cli,organize,rename
Classifier: Development Status :: 4 - Beta
Classifier: Intended Audience :: End Users/Desktop
Classifier: Topic :: Utilities
Classifier: Programming Language :: Python :: 3
Classifier: Programming Language :: Python :: 3.7
Classifier: Programming Language :: Python :: 3.8
Classifier: Programming Language :: Python :: 3.9
Classifier: Programming Language :: Python :: 3.10
Classifier: Programming Language :: Python :: 3.11
Classifier: Programming Language :: Python :: 3.12
Classifier: Environment :: Console
Classifier: Operating System :: OS Independent
Requires-Python: >=3.7
License-File: LICENSE
Requires-Dist: click>=8.1.0
Requires-Dist: rich>=13.0.0
Requires-Dist: questionary>=2.0.0
Provides-Extra: dev
Requires-Dist: pytest>=7.0.0; extra == "dev"
Requires-Dist: pytest-cov>=4.0.0; extra == "dev"
Requires-Dist: black>=22.0.0; extra == "dev"
Dynamic: home-page
Dynamic: license-file
Dynamic: requires-python
